classification/__init__.py
classification/models.py
classification/result.py
classification/rules.py
classification/utils.py
classification_mega_chem_mesh-0.0.24.1.dist-info/LICENSE
classification_mega_chem_mesh-0.0.24.1.dist-info/METADATA
classification_mega_chem_mesh-0.0.24.1.dist-info/WHEEL
classification_mega_chem_mesh-0.0.24.1.dist-info/top_level.txt
classification_mega_chem_mesh-0.0.24.1.dist-info/RECORD
